kurses/__init__.py
kurses/color.py
kurses-1.1.0.dist-info/METADATA
kurses-1.1.0.dist-info/WHEEL
kurses-1.1.0.dist-info/top_level.txt
kurses-1.1.0.dist-info/RECORD
