Metadata-Version: 2.1
Name: kurses
Version: 1.1.0
Summary: An ascii art game engine
Author: Kellan Butler
Author-email: kellanbutler@email.com
Keywords: curses
Classifier: Development Status :: 4 - Beta
Classifier: Intended Audience :: Developers
Classifier: Programming Language :: Python :: 3
Classifier: Operating System :: MacOS :: MacOS X
Classifier: Operating System :: Microsoft :: Windows
Classifier: Operating System :: POSIX :: Linux
Requires-Dist: getch
